skyblock_repo-1.1.0.dist-info/METADATA
skyblock_repo-1.1.0.dist-info/WHEEL
skyblock_repo/__init__.py
skyblock_repo/skyblock_repo.cpython-312-x86_64-linux-gnu.so
skyblock_repo-1.1.0.dist-info/RECORD
