Metadata-Version: 2.4
Name: skyblock-repo
Version: 1.1.0
Summary: Cargo/Python package to interface with the Skyblock Repo
Keywords: skyblock,hypixel,hypixel-skyblock
Home-Page: https://skyblockrepo.com
License: MIT
Project-URL: Source Code, https://github.com/SkyblockRepo/RepoRS
